{
  "$schema": "http://json-schema.org/draft-04/schema#",
  "@id": null,
  "@type": "https://schema.metadatacenter.org/core/TemplateElement",
  "type": "object",
  "title": "",
  "description": "",
  "_ui": {
    "order": []
  },
  "properties": {
    "@context": {
      "properties": {
        "_value": {
          "enum": [
            "https://schema.org/value"
          ]
        }
      },
      "required": [
        "_value"
      ],
      "additionalProperties": false
    },
    "@id": {
      "format": "uri",
      "type": "string"
    },
    "@type": {
      "oneOf": [
        {
          "type": "string",
          "format": "uri"
        },
        {
          "type": "array",
          "minItems": 1,
          "items": {
            "type": "string",
            "format": "uri"
          },
          "uniqueItems": true
        }
      ]
    },
    "_ui": {
      "title": "",
      "description": ""
    }
  },
  "required": [
    "@id"
  ],
  "additionalProperties": false
}