[
  {
    "cedarType": "textfield",
    "iconClass": "fa fa-font",
    "label": "Text",
    "allowedInElement": true,
    "primaryField": true,
    "hasControlledTerms": true,
    "staticField": false,
    "allowsMultiple": true,
    "allowsValueRecommendation": true,
    "hasInstanceTerm": true,
    "allowsRequired": true
  },
  {
    "cedarType": "attribute-value",
    "iconClass": "fa fa-plus-square",
    "label": "Attribute Value",
    "allowedInElement": true,
    "primaryField": true,
    "hasControlledTerms": false,
    "staticField": false,
    "allowsMultiple": false,
    "allowsValueRecommendation": false,
    "hasInstanceTerm": false,
    "allowsRequired": false
  },
  {
    "cedarType": "link",
    "iconClass": "fa fa-link",
    "label": "link",
    "allowedInElement": true,
    "primaryField": false,
    "hasControlledTerms": false,
    "staticField": false,
    "allowsMultiple": true,
    "allowsValueRecommendation": false,
    "hasInstanceTerm": true,
    "allowsRequired": true
  },
  {
    "cedarType": "textarea",
    "iconClass": "fa fa-paragraph",
    "label": "Text Area",
    "allowedInElement": true,
    "primaryField": false,
    "hasControlledTerms": false,
    "staticField": false,
    "allowsMultiple": true,
    "allowsValueRecommendation": false,
    "hasInstanceTerm": false,
    "allowsRequired": true
  },
  {
    "cedarType": "radio",
    "iconClass": "fa fa-dot-circle-o",
    "label": "Multiple Choice",
    "allowedInElement": true,
    "primaryField": false,
    "hasControlledTerms": false,
    "staticField": false,
    "allowsMultiple": false,
    "allowsValueRecommendation": false,
    "hasInstanceTerm": false,
    "allowsRequired": true
  },
  {
    "cedarType": "checkbox",
    "iconClass": "fa fa-check-square-o",
    "label": "Checkbox",
    "allowedInElement": true,
    "primaryField": false,
    "hasControlledTerms": false,
    "staticField": false,
    "allowsMultiple": false,
    "allowsValueRecommendation": false,
    "hasInstanceTerm": false,
    "allowsRequired": true
  },
  {
    "cedarType": "date",
    "iconClass": "fa fa-calendar",
    "label": "Date",
    "allowedInElement": true,
    "primaryField": true,
    "hasControlledTerms": false,
    "staticField": false,
    "allowsMultiple": true,
    "allowsValueRecommendation": false,
    "hasInstanceTerm": false,
    "allowsRequired": true
  },
  {
    "cedarType": "email",
    "iconClass": "fa fa-envelope",
    "label": "Email",
    "allowedInElement": true,
    "primaryField": false,
    "hasControlledTerms": false,
    "staticField": false,
    "allowsMultiple": true,
    "allowsValueRecommendation": false,
    "hasInstanceTerm": false,
    "allowsRequired": true
  },
  {
    "cedarType": "list",
    "iconClass": "cedar-svg-list",
    "allowedInElement": true,
    "primaryField": false,
    "label": "List",
    "hasControlledTerms": false,
    "staticField": false,
    "allowsMultiple": false,
    "allowsValueRecommendation": false,
    "hasInstanceTerm": false,
    "allowsRequired": true
  },
  {
    "cedarType": "numeric",
    "iconClass": "cedar-svg-numeric",
    "allowedInElement": true,
    "primaryField": true,
    "Label": "Number",
    "hasControlledTerms": false,
    "staticField": false,
    "allowsMultiple": true,
    "allowsValueRecommendation": false,
    "hasInstanceTerm": false,
    "allowsRequired": true
  },
  {
    "cedarType": "phone-number",
    "iconClass": "cedar-svg-phone",
    "allowedInElement": true,
    "label": "Phone Number",
    "primaryField": false,
    "hasControlledTerms": false,
    "staticField": false,
    "allowsMultiple": true,
    "allowsValueRecommendation": false,
    "hasInstanceTerm": false,
    "allowsRequired": true
  },
  {
    "cedarType": "page-break",
    "iconClass": "cedar-svg-page-break",
    "allowedInElement": false,
    "label": "Page Break",
    "primaryField": false,
    "hasControlledTerms": false,
    "staticField": true,
    "allowsMultiple": false,
    "allowsValueRecommendation": false,
    "hasInstanceTerm": false,
    "allowsRequired": false
  },
  {
    "cedarType": "section-break",
    "iconClass": "cedar-svg-section-break",
    "allowedInElement": true,
    "label": "Section Break",
    "primaryField": false,
    "hasControlledTerms": false,
    "staticField": true,
    "allowsMultiple": false,
    "allowsValueRecommendation": false,
    "hasInstanceTerm": false,
    "allowsRequired": false
  },
  {
    "cedarType": "richtext",
    "iconClass": "cedar-svg-rich-text",
    "allowedInElement": true,
    "label": "Rich Text",
    "primaryField": false,
    "hasControlledTerms": false,
    "staticField": true,
    "allowsMultiple": false,
    "allowsValueRecommendation": false,
    "hasInstanceTerm": false,
    "allowsRequired": false
  },
  {
    "cedarType": "image",
    "iconClass": "cedar-svg-image",
    "allowedInElement": true,
    "label": "Image",
    "primaryField": false,
    "hasControlledTerms": false,
    "staticField": true,
    "allowsMultiple": false,
    "allowsValueRecommendation": false,
    "hasInstanceTerm": false,
    "allowsRequired": false
  },
  {
    "cedarType": "youtube",
    "iconClass": "cedar-svg-youtube",
    "allowedInElement": true,
    "label": "YouTube Video",
    "primaryField": false,
    "hasControlledTerms": false,
    "staticField": true,
    "allowsMultiple": false,
    "allowsValueRecommendation": false,
    "hasInstanceTerm": false,
    "allowsRequired": false
  }
]
